th_helpers/__init__.py
th_helpers/components/__init__.py
th_helpers/components/date_picker.py
th_helpers/components/deck_label.py
th_helpers/components/download_button.py
th_helpers/components/help_icon.py
th_helpers/components/matchup_table.py
th_helpers/components/ternary_switch.py
th_helpers/scraper/__init__.py
th_helpers/scraper/limitless.py
th_helpers/scraper/pokedata.py
th_helpers/scraper/utils.py
th_helpers/utils/__init__.py
th_helpers/utils/_icon_color_mapping.py
th_helpers/utils/card_cache.py
th_helpers/utils/cards.py
th_helpers/utils/colors.py
th_helpers/utils/constants.py
th_helpers/utils/date.py
th_helpers/utils/images.py
th_helpers/utils/pokemon.py
th_helpers-0.1.18.dist-info/licenses/LICENSE
th_helpers-0.1.18.dist-info/METADATA
th_helpers-0.1.18.dist-info/WHEEL
th_helpers-0.1.18.dist-info/top_level.txt
th_helpers-0.1.18.dist-info/RECORD
