Metadata-Version: 2.4
Name: th-helpers
Version: 0.1.18
Summary: Helper functions for Trainer Hill
Author-email: Bradley Erickson <bbwe24@gmail.com>
License: MIT License
License-File: LICENSE
Requires-Dist: bs4
Requires-Dist: requests
Dynamic: license-file
